odoo10_addon_l10n_ch_base_bank-10.0.1.3.0-py3.8-nspkg.pth
odoo/addons/l10n_ch_base_bank/README.rst
odoo/addons/l10n_ch_base_bank/__init__.py
odoo/addons/l10n_ch_base_bank/__manifest__.py
odoo/addons/l10n_ch_base_bank/i18n/de.po
odoo/addons/l10n_ch_base_bank/i18n/el_GR.po
odoo/addons/l10n_ch_base_bank/i18n/es.po
odoo/addons/l10n_ch_base_bank/i18n/es_MX.po
odoo/addons/l10n_ch_base_bank/i18n/fr.po
odoo/addons/l10n_ch_base_bank/i18n/hr.po
odoo/addons/l10n_ch_base_bank/i18n/it.po
odoo/addons/l10n_ch_base_bank/i18n/l10n_ch_base_bank.pot
odoo/addons/l10n_ch_base_bank/i18n/nb_NO.po
odoo/addons/l10n_ch_base_bank/i18n/nl.po
odoo/addons/l10n_ch_base_bank/i18n/pt_BR.po
odoo/addons/l10n_ch_base_bank/i18n/pt_PT.po
odoo/addons/l10n_ch_base_bank/i18n/sl.po
odoo/addons/l10n_ch_base_bank/i18n/zh_CN.po
odoo/addons/l10n_ch_base_bank/models/__init__.py
odoo/addons/l10n_ch_base_bank/models/bank.py
odoo/addons/l10n_ch_base_bank/models/invoice.py
odoo/addons/l10n_ch_base_bank/static/description/icon.png
odoo/addons/l10n_ch_base_bank/tests/__init__.py
odoo/addons/l10n_ch_base_bank/tests/test_bank.py
odoo/addons/l10n_ch_base_bank/tests/test_bank_type.py
odoo/addons/l10n_ch_base_bank/tests/test_create_invoice.py
odoo/addons/l10n_ch_base_bank/tests/test_search_invoice.py
odoo/addons/l10n_ch_base_bank/views/bank.xml
odoo/addons/l10n_ch_base_bank/views/invoice.xml
odoo10_addon_l10n_ch_base_bank-10.0.1.3.0.dist-info/METADATA
odoo10_addon_l10n_ch_base_bank-10.0.1.3.0.dist-info/WHEEL
odoo10_addon_l10n_ch_base_bank-10.0.1.3.0.dist-info/namespace_packages.txt
odoo10_addon_l10n_ch_base_bank-10.0.1.3.0.dist-info/top_level.txt
odoo10_addon_l10n_ch_base_bank-10.0.1.3.0.dist-info/RECORD
