Metadata-Version: 2.1
Name: odoo10-addon-l10n-ch-base-bank
Version: 10.0.1.3.0
Summary: Types and number validation for swiss electronic pmnt. DTA, ESR
Home-page: https://github.com/OCA/l10n-switzerland
Author: Camptocamp,Odoo Community Association (OCA)
Author-email: support@odoo-community.org
License: AGPL-3
Platform: UNKNOWN
Classifier: Programming Language :: Python
Classifier: Framework :: Odoo
Classifier: License :: OSI Approved :: GNU Affero General Public License v3
Requires-Python: ~=2.7
Requires-Dist: odoo10-addon-account-payment-partner
Requires-Dist: odoo (<10.1dev,>=10.0)
